fileCrypto/__init__.py
fileCrypto/fileOnA85.py
fileCrypto/fileOnAES.py
fileCrypto/fileOnARC2.py
fileCrypto/fileOnARC4.py
fileCrypto/fileOnBase16.py
fileCrypto/fileOnBase32.py
fileCrypto/fileOnBase64.py
fileCrypto/fileOnBlowfish.py
fileCrypto/fileOnDES.py
fileCrypto/fileOnDES3.py
fileCrypto/fileOnXOR.py
fileCrypto-4.0.1.dist-info/METADATA
fileCrypto-4.0.1.dist-info/WHEEL
fileCrypto-4.0.1.dist-info/top_level.txt
fileCrypto-4.0.1.dist-info/RECORD
