Metadata-Version: 2.1
Name: fileCrypto
Version: 4.0.1
Summary: Protecting File Was Never Easier Than Before
Home-page: https://github.com/ziadab/fileCrypto
Author: Ziad Abouelfarah
Author-email: zain.work02@gmail.com
License: UNKNOWN
Platform: UNKNOWN
Classifier: Programming Language :: Python :: 3
Classifier: License :: OSI Approved :: MIT License
Classifier: Operating System :: OS Independent
